.gitignore
CHANGES.txt
LICENSE.txt
MANIFEST.in
README.txt
bootstrap.py
buildout.cfg
setup.py
js/__init__.py
js.underscore.egg-info/PKG-INFO
js.underscore.egg-info/SOURCES.txt
js.underscore.egg-info/dependency_links.txt
js.underscore.egg-info/entry_points.txt
js.underscore.egg-info/namespace_packages.txt
js.underscore.egg-info/not-zip-safe
js.underscore.egg-info/requires.txt
js.underscore.egg-info/top_level.txt
js/underscore/__init__.py
js/underscore/test_underscore.js.txt
js/underscore/resources/README.txt
js/underscore/resources/underscore-min.js
js/underscore/resources/underscore.js