Metadata-Version: 1.0
Name: js.underscore
Version: 1.5.2
Summary: Fanstatic packaging of underscore.js
Home-page: https://github.com/disko/js.underscore
Author: Andreas Kaiser
Author-email: disko@binary-punks.com
License: BSD
Platform: UNKNOWN
